Metadata-Version: 1.0
Name: msds-distributions
Version: 0.1
Summary: Gaussian and Binomial distributions
Home-page: UNKNOWN
Author: Mauro Sobreira
Author-email: msobreira27@yahoo.com
License: UNKNOWN
Platform: UNKNOWN
